<?xml version="1.0" encoding="UTF-8"?>
<!DOCTYPE sun-ejb-jar PUBLIC "-//Sun Microsystems, Inc.//DTD Application Server 9.0 EJB 3.0//EN" "http://www.sun.com/software/appserver/dtds/sun-ejb-jar_3_0-0.dtd">
<sun-ejb-jar>
  <enterprise-beans>
    <ejb>
      <ejb-name>TipoVotoWS</ejb-name>
      <webservice-endpoint>
        <port-component-name>TipoVotoWS</port-component-name>
        <endpoint-address-uri>pqs_api_glassfish/TipoVotoWSService</endpoint-address-uri>
      </webservice-endpoint>
    </ejb>
    <ejb>
      <ejb-name>PersonaWS</ejb-name>
      <webservice-endpoint>
        <port-component-name>PersonaWS</port-component-name>
        <endpoint-address-uri>pqs_api_glassfish/PersonaWSService</endpoint-address-uri>
      </webservice-endpoint>
    </ejb>
    <ejb>
      <ejb-name>TipoAssenzaWS</ejb-name>
      <webservice-endpoint>
        <port-component-name>TipoAssenzaWS</port-component-name>
        <endpoint-address-uri>pqs_api_glassfish/TipoAssenzaWSService</endpoint-address-uri>
      </webservice-endpoint>
    </ejb>
    <ejb>
      <ejb-name>ContattoWS</ejb-name>
      <webservice-endpoint>
        <port-component-name>ContattoWS</port-component-name>
        <endpoint-address-uri>pqs_api_glassfish/ContattoWSService</endpoint-address-uri>
      </webservice-endpoint>
    </ejb>
    <ejb>
      <ejb-name>ReligioneWS</ejb-name>
      <webservice-endpoint>
        <port-component-name>ReligioneWS</port-component-name>
        <endpoint-address-uri>pqs_api_glassfish/ReligioneWSService</endpoint-address-uri>
      </webservice-endpoint>
    </ejb>
    <ejb>
      <ejb-name>ClasseWS</ejb-name>
      <webservice-endpoint>
        <port-component-name>ClasseWS</port-component-name>
        <endpoint-address-uri>pqs_api_glassfish/ClasseWSService</endpoint-address-uri>
      </webservice-endpoint>
    </ejb>
    <ejb>
      <ejb-name>MateriaInsegnamentoWS</ejb-name>
      <webservice-endpoint>
        <port-component-name>MateriaInsegnamentoWS</port-component-name>
        <endpoint-address-uri>pqs_api_glassfish/MateriaInsegnamentoWSService</endpoint-address-uri>
      </webservice-endpoint>
    </ejb>
    <ejb>
      <ejb-name>WSTest</ejb-name>
      <webservice-endpoint>
        <port-component-name>WSTest</port-component-name>
        <endpoint-address-uri>pqs_api_glassfish/WSTestService</endpoint-address-uri>
      </webservice-endpoint>
    </ejb>
    <ejb>
      <ejb-name>NazioneWS</ejb-name>
      <webservice-endpoint>
        <port-component-name>NazioneWS</port-component-name>
        <endpoint-address-uri>pqs_api_glassfish/NazioneWSService</endpoint-address-uri>
      </webservice-endpoint>
    </ejb>
    <ejb>
      <ejb-name>AssenzaWS</ejb-name>
      <webservice-endpoint>
        <port-component-name>AssenzaWS</port-component-name>
        <endpoint-address-uri>pqs_api_glassfish/AssenzaWSService</endpoint-address-uri>
      </webservice-endpoint>
    </ejb>
    <ejb>
      <ejb-name>TipoProvaWS</ejb-name>
      <webservice-endpoint>
        <port-component-name>TipoProvaWS</port-component-name>
        <endpoint-address-uri>pqs_api_glassfish/TipoProvaWSService</endpoint-address-uri>
      </webservice-endpoint>
    </ejb>
    <ejb>
      <ejb-name>VotoWS</ejb-name>
      <webservice-endpoint>
        <port-component-name>VotoWS</port-component-name>
        <endpoint-address-uri>pqs_api_glassfish/VotoWSService</endpoint-address-uri>
      </webservice-endpoint>
    </ejb>
  </enterprise-beans>
</sun-ejb-jar>
